terminal/__init__.py
terminal/cli.py
terminal/agents/__init__.py
terminal/agents/code_agent.py
terminal/agents/general_agent.py
terminal/agents/shell_agent.py
terminal/core/__init__.py
terminal/core/agent.py
terminal/core/executor.py
terminal/core/router.py
terminal/utils/__init__.py
terminal/utils/commands.py
terminal/utils/config.py
terminal/utils/gemini.py
terminal/utils/os_info.py
terminal/utils/parsers.py
terminal/utils/safety.py
ai_terminal_cli-0.1.6.dist-info/METADATA
ai_terminal_cli-0.1.6.dist-info/WHEEL
ai_terminal_cli-0.1.6.dist-info/entry_points.txt
ai_terminal_cli-0.1.6.dist-info/top_level.txt
ai_terminal_cli-0.1.6.dist-info/RECORD
